{
  "footerLogo": "/assets/images/logo-footer.png",

  "contactsHeading": "Contact Info",
  "contactsInfo":[
    {
      "link":"",
      "text":"Relic Digital"
    },
    {
      "link":"https://goo.gl/maps/fBANt7Ns2wi6mM7cA",
      "text":"200 Biscayne Blvd #614, Miami, FL"
    },
    {
      "link":"tel:305-707-7080",
      "text":"305-707-7080"
    },
    {
      "link":"mailto:",
      "text":"hello@relicdigital.com"
    }
  ],

  "siteMapHeading":"Sitemap",
  "siteMap":[
    {
      "link":"about",
      "text":"About Company"
    },
    {
      "link":"portfolio",
      "text":"Projects"
    },
    {
      "link":"privacy-policy",
      "text":"Privacy Policy"
    },
    {
      "link":"terms-conditions",
      "text":"Terms & Condition"
    }
  ],

  "socialHeading":"Social Media",
  "socialMedia":[
    {
      "link":"#",
      "text":"Medium"
    },
    {
      "link":"#",
      "text":"Behance"
    },
    {
      "link":"#",
      "text":"Dribbble"
    },
    {
      "link":"#",
      "text":"Instagram"
    }
  ],
  
  "brandHeading":"We help brands:",
  "brandMotto":["Check how many of your network are where you want to be.","produce valuable cultural content","create fresh brand experience"],

  "back2topIcon":"/assets/images/to-top.svg",
  "customerComment":"From the top"
}
